zope.i18n-5.2-py3.11-nspkg.pth
zope/i18n/__init__.py
zope/i18n/compile.py
zope/i18n/config.py
zope/i18n/configure.zcml
zope/i18n/format.py
zope/i18n/gettextmessagecatalog.py
zope/i18n/i18nobject.txt
zope/i18n/meta.zcml
zope/i18n/negotiator.py
zope/i18n/simpletranslationdomain.py
zope/i18n/testing.py
zope/i18n/testmessagecatalog.py
zope/i18n/testmessagecatalog.rst
zope/i18n/translationdomain.py
zope/i18n/zcml.py
zope/i18n/interfaces/__init__.py
zope/i18n/interfaces/locales.py
zope/i18n/locales/LocaleElements.dtd
zope/i18n/locales/README.txt
zope/i18n/locales/__init__.py
zope/i18n/locales/configure.zcml
zope/i18n/locales/fallbackcollator.py
zope/i18n/locales/fallbackcollator.txt
zope/i18n/locales/inheritance.py
zope/i18n/locales/provider.py
zope/i18n/locales/xmlfactory.py
zope/i18n/locales/data/aa.xml
zope/i18n/locales/data/aa_DJ.xml
zope/i18n/locales/data/aa_ER.xml
zope/i18n/locales/data/aa_ER_SAAHO.xml
zope/i18n/locales/data/aa_ET.xml
zope/i18n/locales/data/af.xml
zope/i18n/locales/data/af_ZA.xml
zope/i18n/locales/data/am.xml
zope/i18n/locales/data/am_ET.xml
zope/i18n/locales/data/ar.xml
zope/i18n/locales/data/ar_AE.xml
zope/i18n/locales/data/ar_BH.xml
zope/i18n/locales/data/ar_DZ.xml
zope/i18n/locales/data/ar_EG.xml
zope/i18n/locales/data/ar_IN.xml
zope/i18n/locales/data/ar_IQ.xml
zope/i18n/locales/data/ar_JO.xml
zope/i18n/locales/data/ar_KW.xml
zope/i18n/locales/data/ar_LB.xml
zope/i18n/locales/data/ar_LY.xml
zope/i18n/locales/data/ar_MA.xml
zope/i18n/locales/data/ar_OM.xml
zope/i18n/locales/data/ar_QA.xml
zope/i18n/locales/data/ar_SA.xml
zope/i18n/locales/data/ar_SD.xml
zope/i18n/locales/data/ar_SY.xml
zope/i18n/locales/data/ar_TN.xml
zope/i18n/locales/data/ar_YE.xml
zope/i18n/locales/data/az.xml
zope/i18n/locales/data/az_AZ.xml
zope/i18n/locales/data/be.xml
zope/i18n/locales/data/be_BY.xml
zope/i18n/locales/data/bg.xml
zope/i18n/locales/data/bg_BG.xml
zope/i18n/locales/data/bn.xml
zope/i18n/locales/data/bn_IN.xml
zope/i18n/locales/data/byn.xml
zope.i18n-5.2.dist-info/LICENSE.txt
zope.i18n-5.2.dist-info/METADATA
zope.i18n-5.2.dist-info/WHEEL
zope.i18n-5.2.dist-info/namespace_packages.txt
zope.i18n-5.2.dist-info/top_level.txt
zope.i18n-5.2.dist-info/RECORD
