Metadata-Version: 2.1
Name: zope.i18n
Version: 5.2
Summary: Zope Internationalization Support
Home-page: https://github.com/zopefoundation/zope.i18n
Author: Zope Foundation and Contributors
Author-email: zope-dev@zope.dev
License: ZPL 2.1
Keywords: zope3 internationalization localization i18n l10n gettext ICU locale
Classifier: Development Status :: 5 - Production/Stable
Classifier: Environment :: Web Environment
Classifier: Intended Audience :: Developers
Classifier: License :: OSI Approved :: Zope Public License
Classifier: Programming Language :: Python
Classifier: Programming Language :: Python :: 3
Classifier: Programming Language :: Python :: 3.8
Classifier: Programming Language :: Python :: 3.9
Classifier: Programming Language :: Python :: 3.10
Classifier: Programming Language :: Python :: 3.11
Classifier: Programming Language :: Python :: 3.12
Classifier: Programming Language :: Python :: Implementation :: CPython
Classifier: Programming Language :: Python :: Implementation :: PyPy
Classifier: Natural Language :: English
Classifier: Operating System :: OS Independent
Classifier: Topic :: Internet :: WWW/HTTP
Classifier: Framework :: Zope :: 3
Requires-Python: >=3.8
License-File: LICENSE.txt
Requires-Dist: setuptools
Requires-Dist: python-gettext
Requires-Dist: pytz
Requires-Dist: zope.deprecation
Requires-Dist: zope.schema
Requires-Dist: zope.i18nmessageid>=4.3
Requires-Dist: zope.component
Provides-Extra: test
Requires-Dist: zope.component[zcml]; extra == "test"
Requires-Dist: zope.configuration; extra == "test"
Requires-Dist: zope.security; extra == "test"
Requires-Dist: zope.publisher; extra == "test"
Requires-Dist: zope.testing; extra == "test"
Requires-Dist: zope.testrunner; extra == "test"
Provides-Extra: compile
Provides-Extra: zcml
Requires-Dist: zope.component[zcml]; extra == "zcml"
Requires-Dist: zope.configuration; extra == "zcml"
Requires-Dist: zope.security; extra == "zcml"
Provides-Extra: docs
Requires-Dist: Sphinx; extra == "docs"
Requires-Dist: repoze.sphinx.autointerface; extra == "docs"
